Workbook

Sheet Instructions
A1: MS Excel Practical Exam
A2: Total Questions: 30
A3: Difficulty Level: Medium
A4: Syllabus: Formulas, Logical Functions, Lookups, INDEX-MATCH, Pivot Tables & Charts, Data Analysis
A5: Attempt all questions using appropriate Excel tools/functions.

Sheet Sheet1
A3: Row Labels | B3: Sum of Total Sales | O3: Row Labels | P3: Sum of Total Sales
A4: Laptop | B4: 225000 | O4: East | P4: 54000
A5: Mobile | B5: 135000 | O5: North | P5: 150000
A6: Tablet | B6: 54000 | O6: South | P6: 165000
A7: Grand Total | B7: 414000 | O7: West | P7: 45000
O8: Grand Total | P8: 414000

Sheet Sales_Data
H1: 8 | I1: Max Amount | J1: =+MAX(J6:J11) -> 106200
H2: 8 | I2: Min Amount | J2: =+MIN(J6:J11) -> 53100
H3: 1 | I3: 2 | J3: 3
F4: 4 - > | G4: Grand Total | H4: =+SUBTOTAL(9,H6:H11) -> 414000 | I4: =+SUBTOTAL(9,I6:I11) -> 63180 | J4: =+SUBTOTAL(9,J6:J11) -> 477180 | K4: 7 | L4: 5 | M4: 6 | N4: =+SUBTOTAL(9,N6:N9) -> 414000 | O4: 9
A5: Order_ID | B5: Region | C5: Salesperson | D5: Product | E5: Quantity | F5: Unit_Price | G5: Sales_Date | H5: Total Sales | I5: GST Amount | J5: Final Payable Amount | K5: Classify Qty | L5: Total Orders | M5: Region | N5: Total Sales | O5: Month | P5: Left | Q5: Round | R5: Remove Duplicate
A6: 301 | B6: North | C6: Amit | D6: Laptop | E6: 2 | F6: 45000 | G6: 05-01-2025 | H6: =+F6*E6 -> 90000 | I6: =+(VLOOKUP($D6,Product_Master!$A$1:$C$4,3,0)*H6)/100 -> 16200 | J6: =+ROUND(SUM(H6:I6),0) -> 106200 | K6: =+IF(E6>3,"High","Low") -> Low | L6: =+COUNTA(A6:A11) -> 6 | M6: North | N6: =+SUMIF($B$6:$B$11,$M6,$H$6:$H$11) -> 150000 | O6: =+TEXT(G6,"MMM") -> Jan | P6: =+LEFT(C6,2) -> Am | Q6: =+ROUND(F6,-3) -> 45000 | R6: No any
A7: 302 | B7: South | C7: Riya | D7: Mobile | E7: 5 | F7: 15000 | G7: 07-01-2025 | H7: =+F7*E7 -> 75000 | I7: =+(VLOOKUP($D7,Product_Master!$A$1:$C$4,3,0)*H7)/100 -> 9000 | J7: =+ROUND(SUM(H7:I7),0) -> 84000 | K7: =+IF(E7>3,"High","Low") -> High | M7: East | N7: =+SUMIF($B$6:$B$11,$M7,$H$6:$H$11) -> 54000 | O7: =+TEXT(G7,"MMM") -> Jan | P7: =+LEFT(C7,2) -> Ri | Q7: =+ROUND(F7,-3) -> 15000
A8: 303 | B8: East | C8: Kunal | D8: Tablet | E8: 3 | F8: 18000 | G8: 10-01-2025 | H8: =+F8*E8 -> 54000 | I8: =+(VLOOKUP($D8,Product_Master!$A$1:$C$4,3,0)*H8)/100 -> 6480 | J8: =+ROUND(SUM(H8:I8),0) -> 60480 | K8: =+IF(E8>3,"High","Low") -> Low | M8: West | N8: =+SUMIF($B$6:$B$11,$M8,$H$6:$H$11) -> 45000 | O8: =+TEXT(G8,"MMM") -> Jan | P8: =+LEFT(C8,2) -> Ku | Q8: =+ROUND(F8,-3) -> 18000
A9: 304 | B9: West | C9: Neha | D9: Laptop | E9: 1 | F9: 45000 | G9: 12-01-2025 | H9: =+F9*E9 -> 45000 | I9: =+(VLOOKUP($D9,Product_Master!$A$1:$C$4,3,0)*H9)/100 -> 8100 | J9: =+ROUND(SUM(H9:I9),0) -> 53100 | K9: =+IF(E9>3,"High","Low") -> Low | M9: South | N9: =+SUMIF($B$6:$B$11,$M9,$H$6:$H$11) -> 165000 | O9: =+TEXT(G9,"MMM") -> Jan | P9: =+LEFT(C9,2) -> Ne | Q9: =+ROUND(F9,-3) -> 45000
A10: 305 | B10: North | C10: Amit | D10: Mobile | E10: 4 | F10: 15000 | G10: 15-01-2025 | H10: =+F10*E10 -> 60000 | I10: =+(VLOOKUP($D10,Product_Master!$A$1:$C$4,3,0)*H10)/100 -> 7200 | J10: =+ROUND(SUM(H10:I10),0) -> 67200 | K10: =+IF(E10>3,"High","Low") -> High | O10: =+TEXT(G10,"MMM") -> Jan | P10: =+LEFT(C10,2) -> Am | Q10: =+ROUND(F10,-3) -> 15000
A11: 306 | B11: South | C11: Riya | D11: Laptop | E11: 2 | F11: 45000 | G11: 18-01-2025 | H11: =+F11*E11 -> 90000 | I11: =+(VLOOKUP($D11,Product_Master!$A$1:$C$4,3,0)*H11)/100 -> 16200 | J11: =+ROUND(SUM(H11:I11),0) -> 106200 | K11: =+IF(E11>3,"High","Low") -> Low | O11: =+TEXT(G11,"MMM") -> Jan | P11: =+LEFT(C11,2) -> Ri | Q11: =+ROUND(F11,-3) -> 45000
J14: 10
A15: Order_ID | B15: Region | C15: Salesperson | D15: Product | E15: Quantity | F15: Unit_Price | G15: Sales_Date | H15: Total Sales | I15: GST Amount | J15: Final Payable Amount | K15: Category | L15: Order_ID | M15: Index_Matc
A16: 301 | B16: North | C16: Amit | D16: Laptop | E16: 2 | F16: 45000 | G16: 05-01-2025 | H16: =+F16*E16 -> 90000 | I16: =+(VLOOKUP($D16,Product_Master!$A$1:$C$4,3,0)*H16)/100 -> 16200 | J16: =+ROUND(SUM(H16:I16),0) -> 106200 | K16: Electronics | L16: 301 | M16: =+INDEX($K$16:$K$21,MATCH($D16,$D$16:$D$21,0)) -> Electronics | O16: {=+_xlfn._xlws.FILTER(A16:A21,(D16:D21="Laptop")*(E16:E21>1))} -> 301
A17: 306 | B17: South | C17: Riya | D17: Laptop | E17: 2 | F17: 45000 | G17: 18-01-2025 | H17: =+F17*E17 -> 90000 | I17: =+(VLOOKUP($D17,Product_Master!$A$1:$C$4,3,0)*H17)/100 -> 16200 | J17: =+ROUND(SUM(H17:I17),0) -> 106200 | K17: Electronics | M17: =+INDEX($K$16:$K$21,MATCH($D17,$D$16:$D$21,0)) -> Electronics | O17: 306
A18: 302 | B18: South | C18: Riya | D18: Mobile | E18: 5 | F18: 15000 | G18: 07-01-2025 | H18: =+F18*E18 -> 75000 | I18: =+(VLOOKUP($D18,Product_Master!$A$1:$C$4,3,0)*H18)/100 -> 9000 | J18: =+ROUND(SUM(H18:I18),0) -> 84000 | K18: Electronics | M18: =+INDEX($K$16:$K$21,MATCH($D18,$D$16:$D$21,0)) -> Electronics
A19: 305 | B19: North | C19: Amit | D19: Mobile | E19: 4 | F19: 15000 | G19: 15-01-2025 | H19: =+F19*E19 -> 60000 | I19: =+(VLOOKUP($D19,Product_Master!$A$1:$C$4,3,0)*H19)/100 -> 7200 | J19: =+ROUND(SUM(H19:I19),0) -> 67200 | K19: Electronics | M19: =+INDEX($K$16:$K$21,MATCH($D19,$D$16:$D$21,0)) -> Electronics
A20: 303 | B20: East | C20: Kunal | D20: Tablet | E20: 3 | F20: 18000 | G20: 10-01-2025 | H20: =+F20*E20 -> 54000 | I20: =+(VLOOKUP($D20,Product_Master!$A$1:$C$4,3,0)*H20)/100 -> 6480 | J20: =+ROUND(SUM(H20:I20),0) -> 60480 | K20: Electronics | M20: =+INDEX($K$16:$K$21,MATCH($D20,$D$16:$D$21,0)) -> Electronics
A21: 304 | B21: West | C21: Neha | D21: Laptop | E21: 1 | F21: 45000 | G21: 12-01-2025 | H21: =+F21*E21 -> 45000 | I21: =+(VLOOKUP($D21,Product_Master!$A$1:$C$4,3,0)*H21)/100 -> 8100 | J21: =+ROUND(SUM(H21:I21),0) -> 53100 | K21: Electronics | M21: =+INDEX($K$16:$K$21,MATCH($D21,$D$16:$D$21,0)) -> Electronics
B24: North Region Laptop Order | C24: =+COUNTIFS($D$16:$D$21,D16,$B$16:$B$21,B16) -> 1

Sheet Product_Master
A1: Product | B1: Category | C1: GST_% | E1: 11
A2: Laptop | B2: Electronics | C2: 18 | D2: =+A2 -> Laptop | E2: =+INDEX($B$2:$B$4,MATCH($D2,$A$2:$A$4,0)) -> Electronics
A3: Mobile | B3: Electronics | C3: 12 | D3: =+A3 -> Mobile | E3: =+INDEX($B$2:$B$4,MATCH($D3,$A$2:$A$4,0)) -> Electronics
A4: Tablet | B4: Electronics | C4: 12 | D4: =+A4 -> Tablet | E4: =+INDEX($B$2:$B$4,MATCH($D4,$A$2:$A$4,0)) -> Electronics

Sheet 123
H1: =+AVERAGE(H3:H7) -> 78.2
A2: Student_ID | B2: Name | C2: Maths | D2: Statistics | E2: Excel | F2: Attendance_% | G2: Total Marks | H2: Avg Marks | I2: Top Performer | J2: Eligible Criteria | K2: STD ID & Name
A3: 1 | B3: Rahul | C3: 78 | D3: 82 | E3: 85 | F3: 92 | G3: =+SUM(C3:E3) -> 245 | H3: =+ROUND(AVERAGE(C3:E3),0) -> 82 | I3: =+IF(H3>=$H$1,"Topper","") -> Topper | J3: =+IF(F3>=85,"Eligible","Not Eligible") -> Eligible | K3: =+_xlfn.CONCAT(B3," - ",A3) -> Rahul - 1
A4: 2 | B4: Sneha | C4: 88 | D4: 91 | E4: 90 | F4: 96 | G4: =+SUM(C4:E4) -> 269 | H4: =+ROUND(AVERAGE(C4:E4),0) -> 90 | I4: =+IF(H4>=$H$1,"Topper","") -> Topper | J4: =+IF(F4>=85,"Eligible","Not Eligible") -> Eligible | K4: =+_xlfn.CONCAT(B4," - ",A4) -> Sneha - 2
A5: 3 | B5: Arjun | C5: 65 | D5: 70 | E5: 72 | F5: 85 | G5: =+SUM(C5:E5) -> 207 | H5: =+ROUND(AVERAGE(C5:E5),0) -> 69 | I5: =+IF(H5>=$H$1,"Topper","") | J5: =+IF(F5>=85,"Eligible","Not Eligible") -> Eligible | K5: =+_xlfn.CONCAT(B5," - ",A5) -> Arjun - 3
A6: 4 | B6: Pooja | C6: 92 | D6: 89 | E6: 94 | F6: 98 | G6: =+SUM(C6:E6) -> 275 | H6: =+ROUND(AVERAGE(C6:E6),0) -> 92 | I6: =+IF(H6>=$H$1,"Topper","") -> Topper | J6: =+IF(F6>=85,"Eligible","Not Eligible") -> Eligible | K6: =+_xlfn.CONCAT(B6," - ",A6) -> Pooja - 4
A7: 5 | B7: Vikas | C7: 55 | D7: 60 | E7: 58 | F7: 80 | G7: =+SUM(C7:E7) -> 173 | H7: =+ROUND(AVERAGE(C7:E7),0) -> 58 | I7: =+IF(H7>=$H$1,"Topper","") | J7: =+IF(F7>=85,"Eligible","Not Eligible") -> Not Eligible | K7: =+_xlfn.CONCAT(B7," - ",A7) -> Vikas - 5
B9: Count of Student | C9: >90% | D9: =+COUNTIF(F3:F7,">90") -> 3
B10: Median of Stats | D10: =+MEDIAN(D3:D7) -> 82
B11: Std. Dev. Of Excel | D11: =+_xlfn.STDEV.P(E3:E7) -> 13.181806

Sheet Questions
A1: 1. Calculate Total Sales for each order (Quantity × Unit_Price). | J1: 2
A2: 2. Calculate GST Amount using VLOOKUP from Product_Master. | J2: 2
A3: 3. Find Final Amount payable (Total Sales + GST). | J3: 2
A4: 4. Find Grand Total of Final Amount. | J4: 2
A5: 5. Count total number of orders using COUNTA. | J5: 2
A6: 6. Find Region-wise total sales using SUMIF. | J6: 2
A7: 7. Use IF to classify Quantity as High (>3) or Low (<=3). | J7: 2
A8: 8. Find the maximum and minimum Final Amount. | J8: 2
A9: 9. Extract month name from Sales_Date. | J9: 2
A10: 10. Sort Sales_Data by Final Amount (Descending). | J10: 2
A11: 11. Use INDEX-MATCH to fetch Product Category. | J11: 2
A12: 12. Calculate average marks of each student. | J12: 2
... A30: 30. Protect the Student_Marks sheet. | J30: 2
J32: =SUM(J1:J30) -> 60
